README.md
setup.cfg
setup.py
ecdaa/__init__.py
ecdaa/wrapper.py
ecdaa_python.egg-info/PKG-INFO
ecdaa_python.egg-info/SOURCES.txt
ecdaa_python.egg-info/dependency_links.txt
ecdaa_python.egg-info/top_level.txt