Metadata-Version: 1.0
Name: ecdaa-python
Version: 0.6.1
Summary: Python wrapper for Elliptic-curve Direct Anonymous Attestation
Home-page: https://github.com/xaptum/ecdaa-python
Author: Xaptum, Inc.
Author-email: sales@xaptum.com
License: Apache 2.0
Platform: UNKNOWN
